elucidate/__init__.py
elucidate/client.py
elucidate/model.py
elucidate/tools.py
elucidate_client-0.1.0.dist-info/entry_points.txt
elucidate_client-0.1.0.dist-info/LICENSE
elucidate_client-0.1.0.dist-info/WHEEL
elucidate_client-0.1.0.dist-info/METADATA
elucidate_client-0.1.0.dist-info/RECORD
