Metadata-Version: 2.1
Name: elucidate-client
Version: 0.1.0
Summary: Python client to interact with an elicidate server
Home-page: https://github.com/knaw-huc/elucidate-python-client
License: MIT
Author: Bram Buitendijk
Author-email: bram.buitendijk@di.huc.knaw.nl
Requires-Python: >=3.7,<4.0
Classifier: Intended Audience :: Developers
Classifier: License :: OSI Approved :: MIT License
Classifier: Operating System :: OS Independent
Classifier: Programming Language :: Python :: 3
Classifier: Programming Language :: Python :: 3.10
Classifier: Programming Language :: Python :: 3.7
Classifier: Programming Language :: Python :: 3.8
Classifier: Programming Language :: Python :: 3.9
Requires-Dist: requests (>=2.27.1,<3.0.0)
Project-URL: Bug Tracker, https://github.com/knaw-huc/elucidate-python-client/issues
Project-URL: Repository, https://github.com/knaw-huc/elucidate-python-client
